tezkormath/__init__.py
tezkormath/main.py
tezkormath-0.0.1.dist-info/METADATA
tezkormath-0.0.1.dist-info/WHEEL
tezkormath-0.0.1.dist-info/top_level.txt
tezkormath-0.0.1.dist-info/RECORD
